mathx/__init__.py
mathx/fit.py
mathx/geometry.py
mathx/interpolation.py
mathx/iteralg.py
mathx/lattices.py
mathx/matseq/README.md
mathx/matseq/__init__.py
mathx/matseq/matseq.py
mathx/matseq/test_matseq.py
mathx/moments.py
mathx/numba.py
mathx/numpyx.py
mathx/ode/__init__.py
mathx/ode/drive.py
mathx/ode/model_systems.py
mathx/ode/rk45.py
mathx/ode/splitstep.py
mathx/ode/test_ode/test_drive.py
mathx/phase/__init__.py
mathx/phase/phase.py
mathx/phase/test_phase.py
mathx/qdht/README.md
mathx/qdht/__init__.py
mathx/qdht/qdht.py
mathx/qdht/test_qdht.py
mathx/sft/__init__.py
mathx/sft/sft.py
mathx/sft/test_sft.py
mathx/sigproc.py
mathx/spfun.py
mathx/test/test_all.py
mathx/test/test_fit.py
mathx/test/test_phase.py
mathx/test/test_sigproc.py
mathx/test/test_usv.py
mathx/test/test_vectorize.py
mathx/usv.py
mathx/vectorize.py
mathx-0.2.2.dist-info/LICENSE
mathx-0.2.2.dist-info/WHEEL
mathx-0.2.2.dist-info/METADATA
mathx-0.2.2.dist-info/RECORD
