Metadata-Version: 2.1
Name: mathx
Version: 0.2.2
Summary: Array handling and mathematics built on top of numpy and scipy.
Home-page: https://github.com/draustin/mathx
License: MIT
Author: Dane Austin
Author-email: dane_austin@fastmail.com.au
Requires-Python: >=3.6,<4.0
Classifier: License :: OSI Approved :: MIT License
Classifier: Programming Language :: Python :: 3
Classifier: Programming Language :: Python :: 3.6
Classifier: Programming Language :: Python :: 3.7
Classifier: Programming Language :: Python :: 3.8
Classifier: Programming Language :: Python :: 3.9
Requires-Dist: numba (>=0.52.0); python_version >= "3.6" and python_version < "3.9"
Requires-Dist: numpy (>=1.18.4,<2.0.0)
Requires-Dist: scipy (>=1.4.1,<2.0.0)
Project-URL: Repository, https://github.com/draustin/mathx
